medsegbench/__init__.py
medsegbench/checkpoint.py
medsegbench/dataset.py
medsegbench/info.py
medsegbench/utils.py
medsegbench-1.0.0.dist-info/LICENSE
medsegbench-1.0.0.dist-info/METADATA
medsegbench-1.0.0.dist-info/WHEEL
medsegbench-1.0.0.dist-info/top_level.txt
medsegbench-1.0.0.dist-info/zip-safe
medsegbench-1.0.0.dist-info/RECORD
