Metadata-Version: 2.1
Name: medsegbench
Version: 1.0.0
Summary: MedSegBench: A Comprehensive Benchmark for Medical Image Segmentation in Diverse Data Modalities
Home-page: https://github.com/zekikus/MedSegBench
Author: Musa Aydin and Zeki Kuş
Author-email: maydin@fsm.edu.tr;zkus@fsm.edu.tr
License: Apache-2.0 License
Classifier: License :: OSI Approved :: Apache Software License
Classifier: Programming Language :: Python
Classifier: Programming Language :: Python :: 3 :: Only
Requires-Python: >=3.6.0
License-File: LICENSE
Requires-Dist: numpy
Requires-Dist: scikit-learn
Requires-Dist: scikit-image
Requires-Dist: Pillow
Requires-Dist: torch
Requires-Dist: torchvision
Requires-Dist: segmentation-models-pytorch
